attrs_xml/README.md
attrs_xml/__init__.py
attrs_xml/elements_registry.py
attrs_xml/formatting.py
attrs_xml/globals.py
attrs_xml/core/__init__.py
attrs_xml/core/base_element.py
attrs_xml/core/converter_factory.py
attrs_xml/core/decorators.py
attrs_xml/core/decorators_utils.py
attrs_xml/core/field_transformer.py
attrs_xml/core/fields.py
attrs_xml/core/inspect.py
attrs_xml/core/protocols.py
attrs_xml/core/sentinels.py
attrs_xml/core/type_utils.py
attrs_xml/core/validator_factory.py
attrs_xml/resolution/__init__.py
attrs_xml/resolution/registry.py
attrs_xml/resolution/strategies.py
attrs_xml/xml/__init__.py
attrs_xml/xml/converter.py
attrs_xml/xml/converters.py
attrs_xml/xml/custom_disambiguator.py
attrs_xml/xml/io.py
attrs_xml/xml/utils.py
ptr_compare/__init__.py
ptr_editor/__init__.py
ptr_editor/html.py
ptr_editor/py.typed
ptr_editor/accessors/__init__.py
ptr_editor/accessors/accessor.py
ptr_editor/accessors/attrs_dict_accessor.py
ptr_editor/agm_config/__init__.py
ptr_editor/agm_config/agm_config.py
ptr_editor/agm_config/agm_utils.py
ptr_editor/agm_config/html.py
ptr_editor/agm_validator/__init__.py
ptr_editor/agm_validator/agm_config_validator.py
ptr_editor/context/README.md
ptr_editor/context/__init__.py
ptr_editor/context/defaults.py
ptr_editor/context/presets.py
ptr_editor/context/service_config.py
ptr_editor/context/services.py
ptr_editor/core/__init__.py
ptr_editor/core/codenames_gen.py
ptr_editor/core/logging.py
ptr_editor/core/ptr_element.py
ptr_editor/core/tree_utils.py
ptr_editor/data/__init__.py
ptr_editor/data/snippets.txt
ptr_editor/diffing/__init__.py
ptr_editor/diffing/diff_report.py
ptr_editor/diffing/matcher.py
ptr_editor/diffing/timeline_differ_simple.py
ptr_editor/diffing/visualize.py
ptr_editor/diffing/xml_diff_result.py
ptr_editor/elements/__init__.py
ptr_editor/elements/additional_elements.py
ptr_editor/elements/agm_config.py
ptr_editor/elements/array.py
ptr_editor/elements/attitude.py
ptr_editor/elements/blocks.py
ptr_editor-0.1.0.dist-info/METADATA
ptr_editor-0.1.0.dist-info/WHEEL
ptr_editor-0.1.0.dist-info/entry_points.txt
ptr_editor-0.1.0.dist-info/licenses/LICENSE
ptr_editor-0.1.0.dist-info/RECORD
