Metadata-Version: 2.4
Name: ptr-editor
Version: 0.1.0
Summary: Utilities to edit PTR files.
Project-URL: documentation, https://luca-penasa.github.io/ptr-editor
Project-URL: homepage, https://luca-penasa.github.io/ptr-editor
Project-URL: repository, https://github.com/luca-penasa/ptr-editor
Author-email: Luca Penasa <luca.penasa@inaf.it>, Benoît Seignovert <benoit.seignovert@univ-nantes.fr>
License-Expression: MIT
License-File: LICENSE
Classifier: Development Status :: 3 - Alpha
Classifier: Intended Audience :: Developers
Classifier: Operating System :: OS Independent
Classifier: Programming Language :: Python
Classifier: Programming Language :: Python :: 3
Classifier: Programming Language :: Python :: 3.11
Classifier: Programming Language :: Python :: 3.12
Classifier: Programming Language :: Python :: 3.13
Classifier: Topic :: Software Development :: Libraries :: Python Modules
Classifier: Typing :: Typed
Requires-Python: <4.0,>=3.11
Requires-Dist: cattrs>=24
Requires-Dist: haikunator>=2.1.0
Requires-Dist: importlib-metadata<9,>=8.5.0
Requires-Dist: jsonschema>=4.0.0
Requires-Dist: loguru<0.8,>=0.7.2
Requires-Dist: lxml>=6.0.2
Requires-Dist: openpyxl>=3.1.5
Requires-Dist: pandas<3,>=2.2.3
Requires-Dist: pint>=0.24.4
Requires-Dist: planetary-coverage>=1.2.0
Requires-Dist: platformdirs>=4.4.0
Requires-Dist: plotly>=5
Requires-Dist: ptwrapper>=2.7.0
Requires-Dist: python-dotenv>=1.0.0
Requires-Dist: pyyaml>=6.0.3
Requires-Dist: quick-spice-manager>=0.0.3
Requires-Dist: requests-cache>=1.2.1
Requires-Dist: requests>=2.31.0
Requires-Dist: xmldiff>=2.7.0
Requires-Dist: xmltodict>=0.14.2
